<metadata xml:lang="fi"><Esri><CreaDate>20160922</CreaDate><CreaTime>11292900</CreaTime><ArcGISFormat>1.0</ArcGISFormat><SyncOnce>TRUE</SyncOnce><ModDate>20161104</ModDate><ModTime>15001300</ModTime><scaleRange><minScale>150000000</minScale><maxScale>5000</maxScale></scaleRange><ArcGISProfile>ItemDescription</ArcGISProfile></Esri><tool name="LogisticRegressionTool" displayname="Logistic regression" toolboxalias="ArcSDM" xmlns=""><arcToolboxHelpPath>c:\program files (x86)\arcgis\desktop10.4\Help\gp</arcToolboxHelpPath><parameters><param name="Input_evidence_raster_layers" displayname="Input Raster Layer(s)" type="Required" direction="Input" datatype="Value Table" expression="Evidence raster;Evidence raster..."><dialogReference>&lt;DIV STYLE="text-align:Left;"&gt;&lt;DIV&gt;&lt;P&gt;&lt;SPAN&gt;Input evidence raster layers. &lt;/SPAN&gt;&lt;/P&gt;&lt;/DIV&gt;&lt;/DIV&gt;</dialogReference></param><param name="Evidence_Type" displayname="Evidence type" type="Required" direction="Input" datatype="Value Table" expression="Evidence type;Evidence type..."><dialogReference>&lt;DIV STYLE="text-align:Left;"&gt;&lt;DIV&gt;&lt;DIV&gt;&lt;P&gt;&lt;SPAN&gt;The evidence type determines how the evidence is used in the logistic regression and how many coefficients are determined. If the type is ordered, then only one coefficient will be determined for the evidence. If the type is free, which means categorical evidence, then a coefficient will be determined for each Gen_class in the free evidence.&lt;/SPAN&gt;&lt;/P&gt;&lt;P&gt;&lt;SPAN&gt;Acceptable values are 'ordered' and 'free'. &lt;/SPAN&gt;&lt;/P&gt;&lt;P&gt;&lt;SPAN&gt;Ordered can be entered more simply as an O or o. &lt;/SPAN&gt;&lt;/P&gt;&lt;P&gt;&lt;SPAN&gt;Categorical can be entered more simply as f, F, C, or c. &lt;/SPAN&gt;&lt;/P&gt;&lt;/DIV&gt;&lt;/DIV&gt;&lt;/DIV&gt;</dialogReference></param><param name="input_weights_tables" displayname="Input weights tables" type="Required" direction="Input" datatype="Value Table" expression="Weights table;Weights table..."><dialogReference>&lt;DIV STYLE="text-align:Left;"&gt;&lt;DIV&gt;&lt;DIV&gt;&lt;P&gt;&lt;SPAN&gt;Weights tables for each evidence layer. &lt;/SPAN&gt;&lt;/P&gt;&lt;/DIV&gt;&lt;/DIV&gt;&lt;/DIV&gt;</dialogReference></param><param name="training_sites" displayname="Training sites" type="Required" direction="Input" datatype="Feature Layer" expression="training_sites"><dialogReference>&lt;DIV STYLE="text-align:Left;"&gt;&lt;DIV&gt;&lt;P&gt;&lt;SPAN&gt;Input training sites feature layer.&lt;/SPAN&gt;&lt;/P&gt;&lt;/DIV&gt;&lt;/DIV&gt;</dialogReference></param><param name="Missing_Data_Value" displayname="Missing data value" type="Required" direction="Output" datatype="Long" expression="Missing_Data_Value"><dialogReference>&lt;DIV STYLE="text-align:Left;"&gt;&lt;DIV&gt;&lt;P&gt;&lt;SPAN&gt;Default missing data value is -99. If this value is not appropriate because it conflicts with valid evidence values, the user can select another negative value. &lt;/SPAN&gt;&lt;/P&gt;&lt;P&gt;&lt;SPAN&gt;The Missing Data value is required to be a negative integer smaller than the other valid values in the evidence raster. &lt;/SPAN&gt;&lt;/P&gt;&lt;/DIV&gt;&lt;/DIV&gt;</dialogReference></param><param name="Unit_Area_sq_km" displayname="Unit area (km^2)" type="Required" direction="Input" datatype="Double" expression="Unit_Area_sq_km"><dialogReference>&lt;DIV STYLE="text-align:Left;"&gt;&lt;DIV&gt;&lt;P&gt;&lt;SPAN&gt;The Unit Area should be the same value used in previous tools used for this model. See the Help file in Calculate Weights for more information on Unit Area. If this tool is being applied to a Fuzzy Logic or Neural Net model enter a value of 1.&lt;/SPAN&gt;&lt;/P&gt;&lt;/DIV&gt;&lt;/DIV&gt;</dialogReference></param><param name="Output_Polynomial_Table" displayname="Output polynomial table" type="Required" direction="Output" datatype="dBASE Table" expression="Output_Polynomial_Table"><dialogReference>&lt;DIV STYLE="text-align:Left;"&gt;&lt;DIV&gt;&lt;DIV&gt;&lt;P&gt;&lt;SPAN&gt;Catalog path of output polynomial dbase table. &lt;/SPAN&gt;&lt;/P&gt;&lt;/DIV&gt;&lt;/DIV&gt;&lt;/DIV&gt;</dialogReference></param><param name="Output_Coefficients_Table" displayname="Output coefficients table" type="Required" direction="Output" datatype="dBASE Table" expression="Output_Coefficients_Table"><dialogReference>&lt;DIV STYLE="text-align:Left;"&gt;&lt;DIV&gt;&lt;DIV&gt;&lt;P&gt;&lt;SPAN&gt;Catalog path of output coefficients dbase table. &lt;/SPAN&gt;&lt;/P&gt;&lt;P&gt;&lt;SPAN /&gt;&lt;/P&gt;&lt;/DIV&gt;&lt;/DIV&gt;&lt;/DIV&gt;</dialogReference></param><param name="Output_Post_Probability_raster" displayname="Output post probablity raster" type="Required" direction="Output" datatype="Raster Dataset" expression="Output_Post_Probability_raster"><dialogReference>&lt;DIV STYLE="text-align:Left;"&gt;&lt;DIV&gt;&lt;DIV&gt;&lt;P&gt;&lt;SPAN&gt;Catalog path of output post-probability raster.&lt;/SPAN&gt;&lt;/P&gt;&lt;/DIV&gt;&lt;/DIV&gt;&lt;/DIV&gt;</dialogReference></param><param name="Output_Standard_Deviation_raster" displayname="Output standard deviation raster" type="Required" direction="Output" datatype="Raster Dataset" expression="Output_Standard_Deviation_raster"><dialogReference>&lt;DIV STYLE="text-align:Left;"&gt;&lt;DIV&gt;&lt;DIV&gt;&lt;P&gt;&lt;SPAN&gt;Catalog path of output standard deviation raster.&lt;/SPAN&gt;&lt;/P&gt;&lt;/DIV&gt;&lt;/DIV&gt;&lt;/DIV&gt;</dialogReference></param><param name="Output_Confidence_raster" displayname="Output confidence raster" type="Required" direction="Output" datatype="Raster Dataset" expression="Output_Confidence_raster"><dialogReference>&lt;DIV STYLE="text-align:Left;"&gt;&lt;DIV&gt;&lt;DIV&gt;&lt;P&gt;&lt;SPAN&gt;Catalog path of output confidence raster&lt;/SPAN&gt;&lt;SPAN&gt;.&lt;/SPAN&gt;&lt;/P&gt;&lt;/DIV&gt;&lt;/DIV&gt;&lt;/DIV&gt;</dialogReference></param></parameters><summary>&lt;DIV STYLE="text-align:Left;"&gt;&lt;DIV&gt;&lt;DIV&gt;&lt;P&gt;&lt;SPAN&gt;This tool is a useful complement to Weights-of-Evidence Calculate Response tool as Logistic Regression does not make the assumption of conditional independence of the evidence with regards to the training sites. Using the evidence and assocaited weights tables, this tool creates the outputs the response and standard deviation rasters. The calculations are based on the Gen_Class attribute in the weights table and the type of evidence.&lt;/SPAN&gt;&lt;/P&gt;&lt;/DIV&gt;&lt;/DIV&gt;&lt;/DIV&gt;</summary></tool><dataIdInfo><idCitation><resTitle>Logistic regression</resTitle></idCitation><idAbs>&lt;DIV STYLE="text-align:Left;"&gt;&lt;DIV&gt;&lt;DIV&gt;&lt;P&gt;&lt;SPAN&gt;This tool is a useful complement to Weights-of-Evidence Calculate Response tool as Logistic Regression does not make the assumption of conditional independence of the evidence with regards to the training sites. Using the evidence and assocaited weights tables, this tool creates the outputs the response and standard deviation rasters. The calculations are based on the Gen_Class attribute in the weights table and the type of evidence.&lt;/SPAN&gt;&lt;/P&gt;&lt;/DIV&gt;&lt;/DIV&gt;&lt;/DIV&gt;</idAbs></dataIdInfo><distInfo><distributor><distorFormat><formatName>ArcToolbox Tool</formatName></distorFormat></distributor></distInfo><mdHrLv><ScopeCd value="005"/></mdHrLv></metadata>
